pipmodule823/__init__.py
pipmodule823/circleinfo.py
pipmodule823-1.0.2.dist-info/METADATA
pipmodule823-1.0.2.dist-info/WHEEL
pipmodule823-1.0.2.dist-info/entry_points.txt
pipmodule823-1.0.2.dist-info/top_level.txt
pipmodule823-1.0.2.dist-info/RECORD
