Metadata-Version: 2.4
Name: pipmodule823
Version: 1.0.2
Summary: Bangladeshi Robi/Airtel Circle Information Tools!
Home-page: https://github.com/ShTasrif
Author: CyberSH
Author-email: cybershbd@gmail.com
License: MIT
Keywords: cybershbd,cyber sh,circleinfo,circle info,circle number to info,circle username to information,circle nickname to information,robi Airtel circle
Classifier: Development Status :: 4 - Beta
Classifier: Intended Audience :: Developers
Classifier: Topic :: Software Development :: Libraries :: Python Modules
Classifier: License :: OSI Approved :: MIT License
Classifier: Programming Language :: Python :: 3
Classifier: Operating System :: OS Independent
Classifier: Environment :: Console
Requires-Python: >=3.9.5
Dynamic: author
Dynamic: author-email
Dynamic: classifier
Dynamic: description
Dynamic: description-content-type
Dynamic: keywords
Dynamic: license
Dynamic: requires-python
Dynamic: summary
